README.md
setup.cfg
setup.py
matrixio_hal/GPIO.py
matrixio_hal/__init__.py
matrixio_hal/bus.py
matrixio_hal/everloop.py
matrixio_hal/matrixio_cpp_hal.pyx
matrixio_hal/sensors.py
python_matrixio_hal.egg-info/PKG-INFO
python_matrixio_hal.egg-info/SOURCES.txt
python_matrixio_hal.egg-info/dependency_links.txt
python_matrixio_hal.egg-info/not-zip-safe
python_matrixio_hal.egg-info/top_level.txt