Metadata-Version: 1.0
Name: python-matrixio-hal
Version: 1.0.1
Summary: Python HAL for the Matrix Creator / Voice wrapping the C++ drivers
Home-page: https://github.com/cmetz/python-matrixio-hal
Author: cmetz
Author-email: christoph.metz@gulp.de
License: MIT
Platform: UNKNOWN
